LICENSE
README.md
pyproject.toml
setup.py
nafflib/__init__.py
nafflib/_version.py
nafflib/backward_compatibility.py
nafflib/naff.py
nafflib/optimize.py
nafflib/toolbox.py
nafflib/windowing.py
nafflib.egg-info/PKG-INFO
nafflib.egg-info/SOURCES.txt
nafflib.egg-info/dependency_links.txt
nafflib.egg-info/requires.txt
nafflib.egg-info/top_level.txt
tests/test_0_backward_compatibility.py
tests/test_1_windowing.py
tests/test_2_optimizer.py
tests/test_3_functionalities.py
tests/test_4_dense_spectrum.py
tests/test_5_henon.py
tests/test_6_lhc.py