Metadata-Version: 2.1
Name: nafflib
Version: 2.0.1
Summary: NAFF algorithm for frequency analysis
Home-page: https://github.com/xsuite/nafflib
Download-URL: https://pypi.python.org/pypi/nafflib
Author: P. Belanger, K. Paraschou et al.
License: Apache 2.0
Project-URL: Bug Tracker, https://github.com/xsuite/xsuite/issues
Project-URL: Source Code, https://github.com/xsuite/nafflib
License-File: LICENSE
Requires-Dist: numpy>=1.0
Requires-Dist: pandas
Requires-Dist: numba
Provides-Extra: tests
Requires-Dist: pytest; extra == "tests"
